redditadminplugins/__init__.py
redditadminplugins/messagecommandprocessor/__init__.py
redditadminplugins/messagecommandprocessor/messagecommandprocessorplugin.py
redditadminplugins/messagecommandprocessor/program/__init__.py
redditadminplugins/messagecommandprocessor/program/commandprocessor.py
redditadminplugins/messagecommandprocessor/program/messagecommandprocessor.py
redditadminplugins/scheduledcrossposter/__init__.py
redditadminplugins/scheduledcrossposter/scheduledcrossposterplugin.py
redditadminplugins/scheduledcrossposter/program/__init__.py
redditadminplugins/scheduledcrossposter/program/completedcrosspostrepository.py
redditadminplugins/scheduledcrossposter/program/scheduledcrosspost.py
redditadminplugins/scheduledcrossposter/program/scheduledcrossposter.py
redditadminplugins/scheduledcrossposter/program/scheduledcrossposterstorage.py
redditadminplugins/scheduledcrossposter/program/scheduledcrosspostrepository.py
redditadminplugins/scheduledposter/__init__.py
redditadminplugins/scheduledposter/scheduledposterplugin.py
redditadminplugins/scheduledposter/program/__init__.py
redditadminplugins/scheduledposter/program/completedsubmissionrepository.py
redditadminplugins/scheduledposter/program/scheduledposter.py
redditadminplugins/scheduledposter/program/scheduledposterstorage.py
redditadminplugins/scheduledposter/program/scheduledsubmission.py
redditadminplugins/scheduledposter/program/scheduledsubmissionrepository.py
redditadminplugins-0.0.5.dist-info/METADATA
redditadminplugins-0.0.5.dist-info/WHEEL
redditadminplugins-0.0.5.dist-info/licenses/LICENSE
redditadminplugins-0.0.5.dist-info/RECORD
